winged/__init__.py
winged/HTML/__init__.py
winged/HTML/a.py
winged/HTML/blockquote.py
winged/HTML/body.py
winged/HTML/br.py
winged/HTML/button.py
winged/HTML/canvas.py
winged/HTML/center.py
winged/HTML/dd.py
winged/HTML/div.py
winged/HTML/dl.py
winged/HTML/doctype.py
winged/HTML/dt.py
winged/HTML/em.py
winged/HTML/fieldset.py
winged/HTML/footer.py
winged/HTML/form.py
winged/HTML/h.py
winged/HTML/head.py
winged/HTML/header.py
winged/HTML/hr.py
winged/HTML/html.py
winged/HTML/i.py
winged/HTML/img.py
winged/HTML/input.py
winged/HTML/label.py
winged/HTML/li.py
winged/HTML/link_rel.py
winged/HTML/main.py
winged/HTML/meta.py
winged/HTML/nav.py
winged/HTML/ol.py
winged/HTML/option.py
winged/HTML/p.py
winged/HTML/pre.py
winged/HTML/script.py
winged/HTML/section.py
winged/HTML/select.py
winged/HTML/span.py
winged/HTML/string.py
winged/HTML/strong.py
winged/HTML/table.py
winged/HTML/tbody.py
winged/HTML/td.py
winged/HTML/textarea.py
winged/HTML/th.py
winged/HTML/thead.py
winged/HTML/title.py
winged/HTML/tr.py
winged/HTML/u.py
winged/HTML/ul.py
winged/core/__init__.py
winged/core/attribute.py
winged/core/attribute_type.py
winged/core/element_abstract.py
winged/core/generic_element.py
winged/core/tag.py
winged_python-0.1.0.dist-info/LICENSE
winged_python-0.1.0.dist-info/METADATA
winged_python-0.1.0.dist-info/WHEEL
winged_python-0.1.0.dist-info/top_level.txt
winged_python-0.1.0.dist-info/RECORD
