Metadata-Version: 2.1
Name: winged-python
Version: 0.1.0
Summary: Winged-Python is an innovative Domain-Specific Language (DSL) library for efficient HTML writing in Python.
Home-page: https://github.com/micheltlutz/winged-python
Author: Michel Anderson Lutz Teixeira
Author-email: hi@micheltlutz.me
License: UNKNOWN
Platform: UNKNOWN
Classifier: License :: OSI Approved :: MIT License
Classifier: Programming Language :: Python :: 3
Classifier: Programming Language :: Python :: 3.11
License-File: LICENSE
